keran_ajaib/__init__.py
keran_ajaib/main.py
keran_ajaib-0.5.dist-info/LICENSE
keran_ajaib-0.5.dist-info/METADATA
keran_ajaib-0.5.dist-info/WHEEL
keran_ajaib-0.5.dist-info/top_level.txt
keran_ajaib-0.5.dist-info/RECORD
