Metadata-Version: 2.2
Name: keran-ajaib
Version: 0.5
License-File: LICENSE
Requires-Dist: certifi==2025.1.31
Requires-Dist: charset-normalizer==3.4.1
Requires-Dist: docutils==0.21.2
Requires-Dist: id==1.5.0
Requires-Dist: idna==3.10
Requires-Dist: jaraco.classes==3.4.0
Requires-Dist: jaraco.context==6.0.1
Requires-Dist: jaraco.functools==4.1.0
Requires-Dist: keyring==25.6.0
Requires-Dist: markdown-it-py==3.0.0
Requires-Dist: mdurl==0.1.2
Requires-Dist: more-itertools==10.6.0
Requires-Dist: nh3==0.2.21
Requires-Dist: packaging==24.2
Requires-Dist: Pygments==2.19.1
Requires-Dist: readme_renderer==44.0
Requires-Dist: requests==2.32.3
Requires-Dist: requests-toolbelt==1.0.0
Requires-Dist: rfc3986==2.0.0
Requires-Dist: rich==13.9.4
Requires-Dist: setuptools==76.0.0
Requires-Dist: twine==6.1.0
Requires-Dist: urllib3==2.3.0
Requires-Dist: wheel==0.45.1
Requires-Dist: merlin-sdk==0.52.0
Dynamic: requires-dist
